coreason_construct/__init__.py
coreason_construct/contexts/library.py
coreason_construct/contexts/registry.py
coreason_construct/data/__init__.py
coreason_construct/data/components.py
coreason_construct/data/library.py
coreason_construct/main.py
coreason_construct/modes/hats.py
coreason_construct/modes/reasoning.py
coreason_construct/primitives/base.py
coreason_construct/primitives/classify.py
coreason_construct/primitives/cohort.py
coreason_construct/primitives/extract.py
coreason_construct/primitives/summarize.py
coreason_construct/roles/base.py
coreason_construct/roles/library.py
coreason_construct/roles/registry.py
coreason_construct/schemas/__init__.py
coreason_construct/schemas/base.py
coreason_construct/schemas/clinical.py
coreason_construct/schemas/primitives.py
coreason_construct/server.py
coreason_construct/utils/__init__.py
coreason_construct/utils/logger.py
coreason_construct/weaver.py
coreason_construct-0.5.0.dist-info/METADATA
coreason_construct-0.5.0.dist-info/WHEEL
coreason_construct-0.5.0.dist-info/licenses/LICENSE
coreason_construct-0.5.0.dist-info/licenses/NOTICE
coreason_construct-0.5.0.dist-info/RECORD
