Metadata-Version: 2.4
Name: coreason_construct
Version: 0.5.0
Summary: coreason-construct
License: # The Prosperity Public License 3.0.0
License-File: LICENSE
License-File: NOTICE
Author: Gowtham A Rao
Author-email: gowtham.rao@coreason.ai
Requires-Python: >=3.11
Classifier: License :: Other/Proprietary License
Classifier: Programming Language :: Python :: 3.12
Classifier: Operating System :: OS Independent
Requires-Dist: anyio (>=4.12.1,<5.0.0)
Requires-Dist: coreason-identity (>=0.4.1,<0.5.0)
Requires-Dist: fastapi
Requires-Dist: httpx (>=0.28.1,<0.29.0)
Requires-Dist: instructor (>=1.0.0,<2.0.0)
Requires-Dist: jinja2 (>=3.1.0,<4.0.0)
Requires-Dist: loguru (>=0.7.2,<0.8.0)
Requires-Dist: pydantic (>=2.0.0,<3.0.0)
Requires-Dist: tiktoken
Requires-Dist: uvicorn[standard]
Project-URL: Documentation, https://github.com/CoReason-AI/coreason-construct
Project-URL: Homepage, https://github.com/CoReason-AI/coreason-construct
Project-URL: Repository, https://github.com/CoReason-AI/coreason-construct
